unifhy/__init__.py
unifhy/component.py
unifhy/data.py
unifhy/model.py
unifhy/settings.py
unifhy/space.py
unifhy/time.py
unifhy/version.py
unifhy/_utils/__init__.py
unifhy/_utils/clock.py
unifhy/_utils/compass.py
unifhy/_utils/exchanger.py
unifhy/_utils/record.py
unifhy/_utils/state.py
unifhy-1.0.0.dist-info/licenses/LICENSE.rst
unifhy-1.0.0.dist-info/METADATA
unifhy-1.0.0.dist-info/WHEEL
unifhy-1.0.0.dist-info/top_level.txt
unifhy-1.0.0.dist-info/RECORD
