Metadata-Version: 2.4
Name: unifhy
Version: 1.0.0
Summary: Unified Framework for Hydrology
Download-URL: https://pypi.python.org/pypi/unifhy
Author: Thibault Hallouin, Richard J. Ellis, Matt Dalle Piagge
License: BSD-3-Clause
Project-URL: Bug Tracker, https://github.com/unifhy-org/unifhy/issues
Project-URL: User Support, https://github.com/unifhy-org/unifhy/discussions
Project-URL: Documentation, https://unifhy-org.github.io/unifhy
Project-URL: Source Code, https://github.com/unifhy-org/unifhy
Classifier: Development Status :: 4 - Beta
Classifier: Natural Language :: English
Classifier: Intended Audience :: Science/Research
Classifier: Topic :: Scientific/Engineering :: Hydrology
Classifier: Operating System :: MacOS
Classifier: Operating System :: POSIX :: Linux
Classifier: Programming Language :: Python
Requires-Python: >=3.8
License-File: LICENSE.rst
Requires-Dist: esmpy
Requires-Dist: netCDF4>=1.5
Requires-Dist: numpy>=1.16
Requires-Dist: pyproj>=3.0
Requires-Dist: pyyaml>=5.3
Requires-Dist: cf-python>=3.16.3
Provides-Extra: docs
Requires-Dist: pydata-sphinx-theme==0.9.0; extra == "docs"
Requires-Dist: sphinx==4.5.0; extra == "docs"
Requires-Dist: sphinx-panels==0.6.0; extra == "docs"
Requires-Dist: netCDF4>=1.5; extra == "docs"
Requires-Dist: numpy>=1.16; extra == "docs"
Requires-Dist: pyproj>=3.0; extra == "docs"
Requires-Dist: pyyaml>=5.3; extra == "docs"
Requires-Dist: esmpy; extra == "docs"
Requires-Dist: cf-python>=3.16.3; extra == "docs"
Provides-Extra: tests
Requires-Dist: cython; extra == "tests"
Dynamic: author
Dynamic: classifier
Dynamic: description
Dynamic: description-content-type
Dynamic: download-url
Dynamic: license
Dynamic: license-file
Dynamic: project-url
Dynamic: provides-extra
Dynamic: requires-dist
Dynamic: requires-python
Dynamic: summary
